[
  {
    "count": 7609,
    "createAt": 1583242244884,
    "date": "2020-03-03"
  },
  {
    "count": 7605,
    "createAt": 1583280980024,
    "date": "2020-03-04"
  },
  {
    "count": 7628,
    "createAt": 1583367460982,
    "date": "2020-03-05"
  },
  {
    "count": 7654,
    "createAt": 1583453876239,
    "date": "2020-03-06"
  },
  {
    "count": 7699,
    "createAt": 1583561552299,
    "date": "2020-03-07"
  },
  {
    "count": 7706,
    "createAt": 1583626710243,
    "date": "2020-03-08"
  },
  {
    "count": 7739,
    "createAt": 1583713111499,
    "date": "2020-03-09"
  },
  {
    "count": 7750,
    "createAt": 1583799482131,
    "date": "2020-03-10"
  },
  {
    "count": 7773,
    "createAt": 1583885935907,
    "date": "2020-03-11"
  },
  {
    "count": 7812,
    "createAt": 1583993644642,
    "date": "2020-03-12"
  },
  {
    "count": 7829,
    "createAt": 1584058750883,
    "date": "2020-03-13"
  },
  {
    "count": 7878,
    "createAt": 1584145135357,
    "date": "2020-03-14"
  }
]