[
  {
    "count": 115955,
    "createAt": 1586661742861,
    "date": "2020-04-12"
  },
  {
    "count": 116006,
    "createAt": 1586736872520,
    "date": "2020-04-13"
  },
  {
    "count": 115291,
    "createAt": 1586844625690,
    "date": "2020-04-14"
  },
  {
    "count": 114914,
    "createAt": 1586909666496,
    "date": "2020-04-15"
  },
  {
    "count": 115933,
    "createAt": 1586996067163,
    "date": "2020-04-16"
  },
  {
    "count": 116289,
    "createAt": 1587082492142,
    "date": "2020-04-17"
  },
  {
    "count": 117072,
    "createAt": 1587168880510,
    "date": "2020-04-18"
  },
  {
    "count": 117322,
    "createAt": 1587255335423,
    "date": "2020-04-19"
  },
  {
    "count": 117433,
    "createAt": 1587341717876,
    "date": "2020-04-20"
  },
  {
    "count": 117326,
    "createAt": 1587428103176,
    "date": "2020-04-21"
  },
  {
    "count": 116081,
    "createAt": 1587514502574,
    "date": "2020-04-22"
  },
  {
    "count": 116449,
    "createAt": 1587600897963,
    "date": "2020-04-23"
  },
  {
    "count": 116963,
    "createAt": 1587687303284,
    "date": "2020-04-24"
  },
  {
    "count": 116403,
    "createAt": 1587773720015,
    "date": "2020-04-25"
  },
  {
    "count": 117095,
    "createAt": 1587860119394,
    "date": "2020-04-26"
  },
  {
    "count": 117081,
    "createAt": 1587946540205,
    "date": "2020-04-27"
  },
  {
    "count": 117515,
    "createAt": 1588032939684,
    "date": "2020-04-28"
  },
  {
    "count": 116711,
    "createAt": 1588119309886,
    "date": "2020-04-29"
  },
  {
    "count": 117379,
    "createAt": 1588205809755,
    "date": "2020-04-30"
  },
  {
    "count": 117655,
    "createAt": 1588292191604,
    "date": "2020-05-01"
  },
  {
    "count": 118008,
    "createAt": 1588378579735,
    "date": "2020-05-02"
  },
  {
    "count": 118221,
    "createAt": 1588464996471,
    "date": "2020-05-03"
  },
  {
    "count": 117965,
    "createAt": 1588551397547,
    "date": "2020-05-04"
  },
  {
    "count": 118217,
    "createAt": 1588659165882,
    "date": "2020-05-05"
  },
  {
    "count": 117604,
    "createAt": 1588724144316,
    "date": "2020-05-06"
  },
  {
    "count": 117898,
    "createAt": 1588810566590,
    "date": "2020-05-07"
  },
  {
    "count": 118337,
    "createAt": 1588896990204,
    "date": "2020-05-08"
  },
  {
    "count": 118484,
    "createAt": 1589026458524,
    "date": "2020-05-09"
  },
  {
    "count": 118458,
    "createAt": 1589069792220,
    "date": "2020-05-10"
  },
  {
    "count": 118104,
    "createAt": 1589156262588,
    "date": "2020-05-11"
  },
  {
    "count": 117377,
    "createAt": 1589263979218,
    "date": "2020-05-12"
  },
  {
    "count": 117177,
    "createAt": 1589329097514,
    "date": "2020-05-13"
  },
  {
    "count": 118115,
    "createAt": 1589415477785,
    "date": "2020-05-14"
  },
  {
    "count": 118508,
    "createAt": 1589501914137,
    "date": "2020-05-15"
  },
  {
    "count": 118849,
    "createAt": 1589588320250,
    "date": "2020-05-16"
  },
  {
    "count": 118544,
    "createAt": 1589674751730,
    "date": "2020-05-17"
  },
  {
    "count": 118086,
    "createAt": 1589761138362,
    "date": "2020-05-18"
  },
  {
    "count": 117501,
    "createAt": 1589847527395,
    "date": "2020-05-19"
  },
  {
    "count": 117026,
    "createAt": 1589933920932,
    "date": "2020-05-20"
  },
  {
    "count": 117256,
    "createAt": 1590020329183,
    "date": "2020-05-21"
  },
  {
    "count": 117191,
    "createAt": 1590106772495,
    "date": "2020-05-22"
  },
  {
    "count": 117036,
    "createAt": 1590194038836,
    "date": "2020-05-23"
  },
  {
    "count": 116858,
    "createAt": 1590280499409,
    "date": "2020-05-24"
  },
  {
    "count": 116244,
    "createAt": 1590366839897,
    "date": "2020-05-25"
  },
  {
    "count": 115447,
    "createAt": 1590453240776,
    "date": "2020-05-26"
  },
  {
    "count": 115011,
    "createAt": 1590539633546,
    "date": "2020-05-27"
  },
  {
    "count": 114987,
    "createAt": 1590626359391,
    "date": "2020-05-28"
  },
  {
    "count": 113924,
    "createAt": 1590712125240,
    "date": "2020-05-29"
  },
  {
    "count": 114410,
    "createAt": 1590798499092,
    "date": "2020-05-30"
  },
  {
    "count": 114016,
    "createAt": 1590884974094,
    "date": "2020-05-31"
  },
  {
    "count": 113836,
    "createAt": 1590971385184,
    "date": "2020-06-01"
  },
  {
    "count": 113132,
    "createAt": 1591057712427,
    "date": "2020-06-02"
  },
  {
    "count": 111739,
    "createAt": 1591144127782,
    "date": "2020-06-03"
  },
  {
    "count": 112644,
    "createAt": 1591230505733,
    "date": "2020-06-04"
  },
  {
    "count": 112842,
    "createAt": 1591316939985,
    "date": "2020-06-05"
  },
  {
    "count": 113086,
    "createAt": 1591424128335,
    "date": "2020-06-06"
  },
  {
    "count": 112088,
    "createAt": 1591532204629,
    "date": "2020-06-07"
  },
  {
    "count": 111813,
    "createAt": 1591576184569,
    "date": "2020-06-08"
  },
  {
    "count": 109897,
    "createAt": 1591662580905,
    "date": "2020-06-09"
  },
  {
    "count": 109532,
    "createAt": 1591769664710,
    "date": "2020-06-10"
  },
  {
    "count": 109520,
    "createAt": 1591835359804,
    "date": "2020-06-11"
  },
  {
    "count": 109631,
    "createAt": 1591921797624,
    "date": "2020-06-12"
  },
  {
    "count": 109620,
    "createAt": 1592008199119,
    "date": "2020-06-13"
  },
  {
    "count": 109453,
    "createAt": 1592094695111,
    "date": "2020-06-14"
  },
  {
    "count": 108951,
    "createAt": 1592181020504,
    "date": "2020-06-15"
  },
  {
    "count": 108538,
    "createAt": 1592267397451,
    "date": "2020-06-16"
  },
  {
    "count": 107629,
    "createAt": 1592353799819,
    "date": "2020-06-17"
  },
  {
    "count": 107641,
    "createAt": 1592440229715,
    "date": "2020-06-18"
  },
  {
    "count": 107692,
    "createAt": 1592526664260,
    "date": "2020-06-19"
  },
  {
    "count": 107729,
    "createAt": 1592633795435,
    "date": "2020-06-20"
  },
  {
    "count": 107260,
    "createAt": 1592699497437,
    "date": "2020-06-21"
  },
  {
    "count": 106649,
    "createAt": 1592785865170,
    "date": "2020-06-22"
  },
  {
    "count": 106341,
    "createAt": 1592872262190,
    "date": "2020-06-23"
  },
  {
    "count": 105507,
    "createAt": 1592958691726,
    "date": "2020-06-24"
  },
  {
    "count": 105664,
    "createAt": 1593045090378,
    "date": "2020-06-25"
  },
  {
    "count": 105246,
    "createAt": 1593131512419,
    "date": "2020-06-26"
  },
  {
    "count": 105243,
    "createAt": 1593217897202,
    "date": "2020-06-27"
  },
  {
    "count": 104877,
    "createAt": 1593304354609,
    "date": "2020-06-28"
  },
  {
    "count": 104507,
    "createAt": 1593393470075,
    "date": "2020-06-29"
  },
  {
    "count": 103644,
    "createAt": 1593497781517,
    "date": "2020-06-30"
  },
  {
    "count": 103325,
    "createAt": 1593563932877,
    "date": "2020-07-01"
  },
  {
    "count": 103422,
    "createAt": 1593650222787,
    "date": "2020-07-02"
  },
  {
    "count": 103388,
    "createAt": 1593736681130,
    "date": "2020-07-03"
  },
  {
    "count": 102947,
    "createAt": 1593843658590,
    "date": "2020-07-04"
  },
  {
    "count": 102669,
    "createAt": 1593909573894,
    "date": "2020-07-05"
  },
  {
    "count": 101881,
    "createAt": 1593995941911,
    "date": "2020-07-06"
  },
  {
    "count": 101711,
    "createAt": 1594082297139,
    "date": "2020-07-07"
  },
  {
    "count": 101379,
    "createAt": 1594168682973,
    "date": "2020-07-08"
  },
  {
    "count": 100895,
    "createAt": 1594255115687,
    "date": "2020-07-09"
  },
  {
    "count": 100240,
    "createAt": 1594341522927,
    "date": "2020-07-10"
  },
  {
    "count": 100539,
    "createAt": 1594427938890,
    "date": "2020-07-11"
  },
  {
    "count": 100189,
    "createAt": 1594517146734,
    "date": "2020-07-12"
  },
  {
    "count": 99177,
    "createAt": 1594600825817,
    "date": "2020-07-13"
  },
  {
    "count": 98971,
    "createAt": 1594687136212,
    "date": "2020-07-14"
  },
  {
    "count": 98789,
    "createAt": 1594773583340,
    "date": "2020-07-15"
  },
  {
    "count": 98716,
    "createAt": 1594902115719,
    "date": "2020-07-16"
  },
  {
    "count": 98678,
    "createAt": 1594946373454,
    "date": "2020-07-17"
  },
  {
    "count": 98534,
    "createAt": 1595032767338,
    "date": "2020-07-18"
  },
  {
    "count": 97758,
    "createAt": 1595139611867,
    "date": "2020-07-19"
  },
  {
    "count": 97258,
    "createAt": 1595205654698,
    "date": "2020-07-20"
  },
  {
    "count": 97033,
    "createAt": 1595292027658,
    "date": "2020-07-21"
  },
  {
    "count": 97051,
    "createAt": 1595378441480,
    "date": "2020-07-22"
  },
  {
    "count": 96882,
    "createAt": 1595464832931,
    "date": "2020-07-23"
  },
  {
    "count": 96921,
    "createAt": 1595551287476,
    "date": "2020-07-24"
  },
  {
    "count": 96936,
    "createAt": 1595637666873,
    "date": "2020-07-25"
  },
  {
    "count": 96468,
    "createAt": 1595724294063,
    "date": "2020-07-26"
  },
  {
    "count": 95463,
    "createAt": 1595810538045,
    "date": "2020-07-27"
  },
  {
    "count": 94809,
    "createAt": 1595938974428,
    "date": "2020-07-28"
  },
  {
    "count": 94802,
    "createAt": 1595983237036,
    "date": "2020-07-29"
  },
  {
    "count": 93836,
    "createAt": 1596069739679,
    "date": "2020-07-30"
  },
  {
    "count": 94034,
    "createAt": 1596156193911,
    "date": "2020-07-31"
  },
  {
    "count": 94119,
    "createAt": 1596242669911,
    "date": "2020-08-01"
  },
  {
    "count": 94269,
    "createAt": 1596329058985,
    "date": "2020-08-02"
  },
  {
    "count": 93910,
    "createAt": 1596415472286,
    "date": "2020-08-03"
  },
  {
    "count": 93027,
    "createAt": 1596501817855,
    "date": "2020-08-04"
  },
  {
    "count": 93677,
    "createAt": 1596588219128,
    "date": "2020-08-05"
  },
  {
    "count": 93725,
    "createAt": 1596674681443,
    "date": "2020-08-06"
  },
  {
    "count": 93642,
    "createAt": 1596761143665,
    "date": "2020-08-07"
  },
  {
    "count": 93382,
    "createAt": 1596847469581,
    "date": "2020-08-08"
  },
  {
    "count": 93221,
    "createAt": 1596934001429,
    "date": "2020-08-09"
  },
  {
    "count": 91866,
    "createAt": 1597020374527,
    "date": "2020-08-10"
  },
  {
    "count": 91544,
    "createAt": 1597106731127,
    "date": "2020-08-11"
  },
  {
    "count": 91376,
    "createAt": 1597193134084,
    "date": "2020-08-12"
  },
  {
    "count": 91914,
    "createAt": 1597279528135,
    "date": "2020-08-13"
  },
  {
    "count": 91292,
    "createAt": 1597386211102,
    "date": "2020-08-14"
  },
  {
    "count": 91114,
    "createAt": 1597452336208,
    "date": "2020-08-15"
  },
  {
    "count": 91092,
    "createAt": 1597538917002,
    "date": "2020-08-16"
  },
  {
    "count": 90608,
    "createAt": 1597625260466,
    "date": "2020-08-17"
  },
  {
    "count": 89488,
    "createAt": 1597711667690,
    "date": "2020-08-18"
  },
  {
    "count": 89648,
    "createAt": 1597798034524,
    "date": "2020-08-19"
  },
  {
    "count": 89595,
    "createAt": 1597884442399,
    "date": "2020-08-20"
  },
  {
    "count": 89372,
    "createAt": 1597970895222,
    "date": "2020-08-21"
  },
  {
    "count": 88695,
    "createAt": 1598057302082,
    "date": "2020-08-22"
  },
  {
    "count": 88441,
    "createAt": 1598143773811,
    "date": "2020-08-23"
  },
  {
    "count": 87373,
    "createAt": 1598230156149,
    "date": "2020-08-24"
  },
  {
    "count": 87919,
    "createAt": 1598336583208,
    "date": "2020-08-25"
  },
  {
    "count": 87943,
    "createAt": 1598402906886,
    "date": "2020-08-26"
  },
  {
    "count": 87650,
    "createAt": 1598489328542,
    "date": "2020-08-27"
  },
  {
    "count": 86823,
    "createAt": 1598576017590,
    "date": "2020-08-28"
  },
  {
    "count": 86525,
    "createAt": 1598660708204,
    "date": "2020-08-29"
  },
  {
    "count": 86119,
    "createAt": 1598747356191,
    "date": "2020-08-30"
  },
  {
    "count": 85911,
    "createAt": 1598833547731,
    "date": "2020-08-31"
  },
  {
    "count": 133,
    "createAt": 1598921663891,
    "date": "2020-09-01"
  },
  {
    "count": 76802,
    "createAt": 1599007917587,
    "date": "2020-09-02"
  },
  {
    "count": 81837,
    "createAt": 1599094343590,
    "date": "2020-09-03"
  },
  {
    "count": 191,
    "createAt": 1599180802779,
    "date": "2020-09-04"
  },
  {
    "count": 827,
    "createAt": 1599269613916,
    "date": "2020-09-05"
  },
  {
    "count": 1474,
    "createAt": 1599353771690,
    "date": "2020-09-06"
  },
  {
    "count": 2059,
    "createAt": 1599440116632,
    "date": "2020-09-07"
  },
  {
    "count": 2182,
    "createAt": 1599526459771,
    "date": "2020-09-08"
  },
  {
    "count": 2501,
    "createAt": 1599612896159,
    "date": "2020-09-09"
  },
  {
    "count": 3015,
    "createAt": 1599699085914,
    "date": "2020-09-10"
  },
  {
    "count": 3637,
    "createAt": 1599785512240,
    "date": "2020-09-11"
  },
  {
    "count": 4837,
    "createAt": 1599872035548,
    "date": "2020-09-12"
  },
  {
    "count": 5422,
    "createAt": 1599958651229,
    "date": "2020-09-13"
  },
  {
    "count": 5959,
    "createAt": 1600044924600,
    "date": "2020-09-14"
  },
  {
    "count": 6115,
    "createAt": 1600131370143,
    "date": "2020-09-15"
  },
  {
    "count": 6459,
    "createAt": 1600217720398,
    "date": "2020-09-16"
  },
  {
    "count": 7350,
    "createAt": 1600304148068,
    "date": "2020-09-17"
  },
  {
    "count": 9698,
    "createAt": 1600453420129,
    "date": "2020-09-18"
  },
  {
    "count": 9940,
    "createAt": 1600476962465,
    "date": "2020-09-19"
  },
  {
    "count": 10678,
    "createAt": 1600563458116,
    "date": "2020-09-20"
  },
  {
    "count": 11012,
    "createAt": 1600649994458,
    "date": "2020-09-21"
  },
  {
    "count": 10981,
    "createAt": 1600736222689,
    "date": "2020-09-22"
  },
  {
    "count": 11303,
    "createAt": 1600822780956,
    "date": "2020-09-23"
  },
  {
    "count": 11675,
    "createAt": 1600909056417,
    "date": "2020-09-24"
  },
  {
    "count": 12598,
    "createAt": 1600995405452,
    "date": "2020-09-25"
  },
  {
    "count": 13638,
    "createAt": 1601081815873,
    "date": "2020-09-26"
  },
  {
    "count": 13750,
    "createAt": 1601168434292,
    "date": "2020-09-27"
  },
  {
    "count": 13695,
    "createAt": 1601254683138,
    "date": "2020-09-28"
  },
  {
    "count": 11766,
    "createAt": 1601341077096,
    "date": "2020-09-29"
  },
  {
    "count": 71712,
    "createAt": 1601945994854,
    "date": "2020-10-06"
  },
  {
    "count": 71779,
    "createAt": 1602032458830,
    "date": "2020-10-07"
  },
  {
    "count": 71492,
    "createAt": 1602118284979,
    "date": "2020-10-08"
  },
  {
    "count": 71210,
    "createAt": 1602205271083,
    "date": "2020-10-09"
  },
  {
    "count": 71399,
    "createAt": 1602291719291,
    "date": "2020-10-10"
  },
  {
    "count": 72012,
    "createAt": 1602378414339,
    "date": "2020-10-11"
  },
  {
    "count": 71986,
    "createAt": 1602464566862,
    "date": "2020-10-12"
  },
  {
    "count": 13092,
    "createAt": 1602551142847,
    "date": "2020-10-13"
  },
  {
    "count": 13459,
    "createAt": 1602637400642,
    "date": "2020-10-14"
  },
  {
    "count": 13283,
    "createAt": 1602724180539,
    "date": "2020-10-15"
  },
  {
    "count": 13723,
    "createAt": 1602810331285,
    "date": "2020-10-16"
  },
  {
    "count": 14690,
    "createAt": 1602896826129,
    "date": "2020-10-17"
  },
  {
    "count": 15764,
    "createAt": 1602983241349,
    "date": "2020-10-18"
  },
  {
    "count": 16286,
    "createAt": 1603069585154,
    "date": "2020-10-19"
  },
  {
    "count": 16465,
    "createAt": 1603155965097,
    "date": "2020-10-20"
  },
  {
    "count": 16712,
    "createAt": 1603242320604,
    "date": "2020-10-21"
  },
  {
    "count": 17376,
    "createAt": 1603328823125,
    "date": "2020-10-22"
  },
  {
    "count": 18302,
    "createAt": 1603415254793,
    "date": "2020-10-23"
  },
  {
    "count": 19375,
    "createAt": 1603501652655,
    "date": "2020-10-24"
  },
  {
    "count": 20217,
    "createAt": 1603588421449,
    "date": "2020-10-25"
  },
  {
    "count": 20988,
    "createAt": 1603674611572,
    "date": "2020-10-26"
  },
  {
    "count": 21047,
    "createAt": 1603760979855,
    "date": "2020-10-27"
  },
  {
    "count": 21483,
    "createAt": 1603866915844,
    "date": "2020-10-28"
  },
  {
    "count": 22043,
    "createAt": 1603933909864,
    "date": "2020-10-29"
  },
  {
    "count": 23120,
    "createAt": 1604018596927,
    "date": "2020-10-30"
  }
]