[
  {
    "count": 3186,
    "createAt": 1586661760832,
    "date": "2020-04-12"
  },
  {
    "count": 3219,
    "createAt": 1586736888073,
    "date": "2020-04-13"
  },
  {
    "count": 3216,
    "createAt": 1586844644187,
    "date": "2020-04-14"
  },
  {
    "count": 3244,
    "createAt": 1586909682903,
    "date": "2020-04-15"
  },
  {
    "count": 3237,
    "createAt": 1586996082836,
    "date": "2020-04-16"
  },
  {
    "count": 3204,
    "createAt": 1587082509321,
    "date": "2020-04-17"
  },
  {
    "count": 3191,
    "createAt": 1587168896568,
    "date": "2020-04-18"
  },
  {
    "count": 3225,
    "createAt": 1587255351564,
    "date": "2020-04-19"
  },
  {
    "count": 3309,
    "createAt": 1587341732665,
    "date": "2020-04-20"
  },
  {
    "count": 3346,
    "createAt": 1587428119761,
    "date": "2020-04-21"
  },
  {
    "count": 3326,
    "createAt": 1587514521794,
    "date": "2020-04-22"
  },
  {
    "count": 3344,
    "createAt": 1587600915963,
    "date": "2020-04-23"
  },
  {
    "count": 3354,
    "createAt": 1587687320690,
    "date": "2020-04-24"
  },
  {
    "count": 3348,
    "createAt": 1587773738071,
    "date": "2020-04-25"
  },
  {
    "count": 3370,
    "createAt": 1587860136188,
    "date": "2020-04-26"
  },
  {
    "count": 3326,
    "createAt": 1587946558304,
    "date": "2020-04-27"
  },
  {
    "count": 3339,
    "createAt": 1588032957135,
    "date": "2020-04-28"
  },
  {
    "count": 3337,
    "createAt": 1588119326795,
    "date": "2020-04-29"
  },
  {
    "count": 3291,
    "createAt": 1588205828631,
    "date": "2020-04-30"
  },
  {
    "count": 3328,
    "createAt": 1588292210599,
    "date": "2020-05-01"
  },
  {
    "count": 3332,
    "createAt": 1588378597392,
    "date": "2020-05-02"
  },
  {
    "count": 3307,
    "createAt": 1588465016033,
    "date": "2020-05-03"
  },
  {
    "count": 3294,
    "createAt": 1588551417512,
    "date": "2020-05-04"
  },
  {
    "count": 3251,
    "createAt": 1588659186268,
    "date": "2020-05-05"
  },
  {
    "count": 3123,
    "createAt": 1588724161842,
    "date": "2020-05-06"
  },
  {
    "count": 3078,
    "createAt": 1588810584081,
    "date": "2020-05-07"
  },
  {
    "count": 3115,
    "createAt": 1588897007633,
    "date": "2020-05-08"
  },
  {
    "count": 3176,
    "createAt": 1589026476651,
    "date": "2020-05-09"
  },
  {
    "count": 3165,
    "createAt": 1589069809063,
    "date": "2020-05-10"
  },
  {
    "count": 3181,
    "createAt": 1589156278463,
    "date": "2020-05-11"
  },
  {
    "count": 3187,
    "createAt": 1589264011972,
    "date": "2020-05-12"
  },
  {
    "count": 3161,
    "createAt": 1589329114125,
    "date": "2020-05-13"
  },
  {
    "count": 3188,
    "createAt": 1589415495206,
    "date": "2020-05-14"
  },
  {
    "count": 3159,
    "createAt": 1589501934131,
    "date": "2020-05-15"
  },
  {
    "count": 3229,
    "createAt": 1589588339833,
    "date": "2020-05-16"
  },
  {
    "count": 3229,
    "createAt": 1589674772140,
    "date": "2020-05-17"
  },
  {
    "count": 3244,
    "createAt": 1589761157930,
    "date": "2020-05-18"
  },
  {
    "count": 3236,
    "createAt": 1589847550593,
    "date": "2020-05-19"
  },
  {
    "count": 3237,
    "createAt": 1589933940951,
    "date": "2020-05-20"
  },
  {
    "count": 3238,
    "createAt": 1590020347878,
    "date": "2020-05-21"
  },
  {
    "count": 3291,
    "createAt": 1590106745324,
    "date": "2020-05-22"
  },
  {
    "count": 3317,
    "createAt": 1590194010673,
    "date": "2020-05-23"
  },
  {
    "count": 3350,
    "createAt": 1590280470485,
    "date": "2020-05-24"
  },
  {
    "count": 3370,
    "createAt": 1590366814176,
    "date": "2020-05-25"
  },
  {
    "count": 3394,
    "createAt": 1590453211265,
    "date": "2020-05-26"
  },
  {
    "count": 3389,
    "createAt": 1590539606245,
    "date": "2020-05-27"
  },
  {
    "count": 3401,
    "createAt": 1590626330836,
    "date": "2020-05-28"
  },
  {
    "count": 3401,
    "createAt": 1590712097065,
    "date": "2020-05-29"
  },
  {
    "count": 3425,
    "createAt": 1590798466223,
    "date": "2020-05-30"
  },
  {
    "count": 3426,
    "createAt": 1590884945001,
    "date": "2020-05-31"
  },
  {
    "count": 3474,
    "createAt": 1590971356237,
    "date": "2020-06-01"
  },
  {
    "count": 3504,
    "createAt": 1591057685740,
    "date": "2020-06-02"
  },
  {
    "count": 3475,
    "createAt": 1591144098933,
    "date": "2020-06-03"
  },
  {
    "count": 3448,
    "createAt": 1591230479496,
    "date": "2020-06-04"
  },
  {
    "count": 3459,
    "createAt": 1591316914574,
    "date": "2020-06-05"
  },
  {
    "count": 3526,
    "createAt": 1591424091578,
    "date": "2020-06-06"
  },
  {
    "count": 3491,
    "createAt": 1591532175235,
    "date": "2020-06-07"
  },
  {
    "count": 3487,
    "createAt": 1591576157005,
    "date": "2020-06-08"
  },
  {
    "count": 3450,
    "createAt": 1591662552792,
    "date": "2020-06-09"
  },
  {
    "count": 3456,
    "createAt": 1591769633733,
    "date": "2020-06-10"
  },
  {
    "count": 3465,
    "createAt": 1591835332721,
    "date": "2020-06-11"
  },
  {
    "count": 3463,
    "createAt": 1591921769285,
    "date": "2020-06-12"
  },
  {
    "count": 3470,
    "createAt": 1592008166848,
    "date": "2020-06-13"
  },
  {
    "count": 3499,
    "createAt": 1592094665941,
    "date": "2020-06-14"
  },
  {
    "count": 3507,
    "createAt": 1592180994469,
    "date": "2020-06-15"
  },
  {
    "count": 3511,
    "createAt": 1592267370383,
    "date": "2020-06-16"
  },
  {
    "count": 3500,
    "createAt": 1592353770482,
    "date": "2020-06-17"
  },
  {
    "count": 3511,
    "createAt": 1592440200222,
    "date": "2020-06-18"
  },
  {
    "count": 3520,
    "createAt": 1592526634030,
    "date": "2020-06-19"
  },
  {
    "count": 3529,
    "createAt": 1592633748394,
    "date": "2020-06-20"
  },
  {
    "count": 3534,
    "createAt": 1592699467950,
    "date": "2020-06-21"
  },
  {
    "count": 3530,
    "createAt": 1592785836277,
    "date": "2020-06-22"
  },
  {
    "count": 3533,
    "createAt": 1592872229561,
    "date": "2020-06-23"
  },
  {
    "count": 3578,
    "createAt": 1592958659293,
    "date": "2020-06-24"
  },
  {
    "count": 3602,
    "createAt": 1593045059752,
    "date": "2020-06-25"
  },
  {
    "count": 3593,
    "createAt": 1593131480168,
    "date": "2020-06-26"
  },
  {
    "count": 3597,
    "createAt": 1593217868111,
    "date": "2020-06-27"
  },
  {
    "count": 3570,
    "createAt": 1593304325919,
    "date": "2020-06-28"
  },
  {
    "count": 3558,
    "createAt": 1593393437377,
    "date": "2020-06-29"
  },
  {
    "count": 3554,
    "createAt": 1593497744313,
    "date": "2020-06-30"
  },
  {
    "count": 3516,
    "createAt": 1593563902056,
    "date": "2020-07-01"
  },
  {
    "count": 3536,
    "createAt": 1593650195633,
    "date": "2020-07-02"
  },
  {
    "count": 3550,
    "createAt": 1593736651813,
    "date": "2020-07-03"
  },
  {
    "count": 3574,
    "createAt": 1593843610668,
    "date": "2020-07-04"
  },
  {
    "count": 3580,
    "createAt": 1593909542964,
    "date": "2020-07-05"
  },
  {
    "count": 3624,
    "createAt": 1593995913469,
    "date": "2020-07-06"
  },
  {
    "count": 3640,
    "createAt": 1594082266147,
    "date": "2020-07-07"
  },
  {
    "count": 3644,
    "createAt": 1594168653494,
    "date": "2020-07-08"
  },
  {
    "count": 3665,
    "createAt": 1594255085694,
    "date": "2020-07-09"
  },
  {
    "count": 3655,
    "createAt": 1594341494205,
    "date": "2020-07-10"
  },
  {
    "count": 3675,
    "createAt": 1594427908980,
    "date": "2020-07-11"
  },
  {
    "count": 3711,
    "createAt": 1594517114413,
    "date": "2020-07-12"
  },
  {
    "count": 3616,
    "createAt": 1594600795141,
    "date": "2020-07-13"
  },
  {
    "count": 3753,
    "createAt": 1594687105684,
    "date": "2020-07-14"
  },
  {
    "count": 3785,
    "createAt": 1594773554338,
    "date": "2020-07-15"
  },
  {
    "count": 3851,
    "createAt": 1594902075385,
    "date": "2020-07-16"
  },
  {
    "count": 3848,
    "createAt": 1594946346797,
    "date": "2020-07-17"
  }
]