[
  {
    "count": 2435,
    "createAt": 1586661564136,
    "date": "2020-04-12"
  },
  {
    "count": 2437,
    "createAt": 1586736714751,
    "date": "2020-04-13"
  },
  {
    "count": 2460,
    "createAt": 1586844398868,
    "date": "2020-04-14"
  },
  {
    "count": 2441,
    "createAt": 1586909498759,
    "date": "2020-04-15"
  },
  {
    "count": 2437,
    "createAt": 1586995908741,
    "date": "2020-04-16"
  },
  {
    "count": 2430,
    "createAt": 1587082317530,
    "date": "2020-04-17"
  },
  {
    "count": 2449,
    "createAt": 1587168714771,
    "date": "2020-04-18"
  },
  {
    "count": 2486,
    "createAt": 1587255167324,
    "date": "2020-04-19"
  },
  {
    "count": 2522,
    "createAt": 1587341551125,
    "date": "2020-04-20"
  },
  {
    "count": 2523,
    "createAt": 1587427940746,
    "date": "2020-04-21"
  },
  {
    "count": 2474,
    "createAt": 1587514337898,
    "date": "2020-04-22"
  },
  {
    "count": 2447,
    "createAt": 1587600735838,
    "date": "2020-04-23"
  },
  {
    "count": 2475,
    "createAt": 1587687147308,
    "date": "2020-04-24"
  }
]