[
  {
    "count": 2369,
    "createAt": 1586661619426,
    "date": "2020-04-12"
  },
  {
    "count": 2408,
    "createAt": 1586736765196,
    "date": "2020-04-13"
  },
  {
    "count": 2459,
    "createAt": 1586844478998,
    "date": "2020-04-14"
  },
  {
    "count": 2453,
    "createAt": 1586909553438,
    "date": "2020-04-15"
  },
  {
    "count": 2476,
    "createAt": 1586995959344,
    "date": "2020-04-16"
  },
  {
    "count": 2495,
    "createAt": 1587082373809,
    "date": "2020-04-17"
  },
  {
    "count": 2525,
    "createAt": 1587168766453,
    "date": "2020-04-18"
  }
]