[
  {
    "count": 10998,
    "createAt": 1583242210552,
    "date": "2020-03-03"
  },
  {
    "count": 10998,
    "createAt": 1583280953766,
    "date": "2020-03-04"
  },
  {
    "count": 10998,
    "createAt": 1583367414919,
    "date": "2020-03-05"
  },
  {
    "count": 10998,
    "createAt": 1583453827247,
    "date": "2020-03-06"
  },
  {
    "count": 11001,
    "createAt": 1583561482970,
    "date": "2020-03-07"
  },
  {
    "count": 11001,
    "createAt": 1583626659079,
    "date": "2020-03-08"
  },
  {
    "count": 11001,
    "createAt": 1583713062704,
    "date": "2020-03-09"
  },
  {
    "count": 11007,
    "createAt": 1583799432414,
    "date": "2020-03-10"
  },
  {
    "count": 11010,
    "createAt": 1583885884407,
    "date": "2020-03-11"
  },
  {
    "count": 11014,
    "createAt": 1583993558548,
    "date": "2020-03-12"
  },
  {
    "count": 11014,
    "createAt": 1584058698444,
    "date": "2020-03-13"
  },
  {
    "count": 11020,
    "createAt": 1584145077179,
    "date": "2020-03-14"
  },
  {
    "count": 11020,
    "createAt": 1584231540409,
    "date": "2020-03-15"
  },
  {
    "count": 11020,
    "createAt": 1584318010793,
    "date": "2020-03-16"
  },
  {
    "count": 11021,
    "createAt": 1584404284500,
    "date": "2020-03-17"
  },
  {
    "count": 11023,
    "createAt": 1584490725218,
    "date": "2020-03-18"
  },
  {
    "count": 11023,
    "createAt": 1584576809296,
    "date": "2020-03-19"
  },
  {
    "count": 11031,
    "createAt": 1584663200515,
    "date": "2020-03-20"
  },
  {
    "count": 11032,
    "createAt": 1584749619292,
    "date": "2020-03-21"
  },
  {
    "count": 11032,
    "createAt": 1584836043328,
    "date": "2020-03-22"
  },
  {
    "count": 11032,
    "createAt": 1584922413905,
    "date": "2020-03-23"
  },
  {
    "count": 11037,
    "createAt": 1585008821141,
    "date": "2020-03-24"
  },
  {
    "count": 11039,
    "createAt": 1585095223118,
    "date": "2020-03-25"
  },
  {
    "count": 11043,
    "createAt": 1585181620415,
    "date": "2020-03-26"
  },
  {
    "count": 11043,
    "createAt": 1585268052108,
    "date": "2020-03-27"
  },
  {
    "count": 11043,
    "createAt": 1585375771873,
    "date": "2020-03-28"
  },
  {
    "count": 11043,
    "createAt": 1585440880377,
    "date": "2020-03-29"
  },
  {
    "count": 11043,
    "createAt": 1585527464757,
    "date": "2020-03-30"
  },
  {
    "count": 11046,
    "createAt": 1585613653675,
    "date": "2020-03-31"
  },
  {
    "count": 11048,
    "createAt": 1585700076521,
    "date": "2020-04-01"
  },
  {
    "count": 11050,
    "createAt": 1585786475735,
    "date": "2020-04-02"
  },
  {
    "count": 11054,
    "createAt": 1585915777371,
    "date": "2020-04-03"
  },
  {
    "count": 11054,
    "createAt": 1585980614638,
    "date": "2020-04-04"
  },
  {
    "count": 11054,
    "createAt": 1586045588903,
    "date": "2020-04-05"
  },
  {
    "count": 11054,
    "createAt": 1586131908476,
    "date": "2020-04-06"
  },
  {
    "count": 11054,
    "createAt": 1586218306207,
    "date": "2020-04-07"
  },
  {
    "count": 11055,
    "createAt": 1586304628837,
    "date": "2020-04-08"
  },
  {
    "count": 11060,
    "createAt": 1586391013230,
    "date": "2020-04-09"
  },
  {
    "count": 11064,
    "createAt": 1586477721782,
    "date": "2020-04-10"
  },
  {
    "count": 11066,
    "createAt": 1586585333150,
    "date": "2020-04-11"
  },
  {
    "count": 11066,
    "createAt": 1586650409175,
    "date": "2020-04-12"
  },
  {
    "count": 11066,
    "createAt": 1586736828387,
    "date": "2020-04-13"
  },
  {
    "count": 11069,
    "createAt": 1586844563741,
    "date": "2020-04-14"
  },
  {
    "count": 11070,
    "createAt": 1586909620583,
    "date": "2020-04-15"
  },
  {
    "count": 11072,
    "createAt": 1586996023474,
    "date": "2020-04-16"
  },
  {
    "count": 11080,
    "createAt": 1587082444272,
    "date": "2020-04-17"
  },
  {
    "count": 11087,
    "createAt": 1587168833615,
    "date": "2020-04-18"
  },
  {
    "count": 11087,
    "createAt": 1587255288540,
    "date": "2020-04-19"
  },
  {
    "count": 11087,
    "createAt": 1587341669651,
    "date": "2020-04-20"
  },
  {
    "count": 11091,
    "createAt": 1587428058422,
    "date": "2020-04-21"
  },
  {
    "count": 11100,
    "createAt": 1587514455804,
    "date": "2020-04-22"
  },
  {
    "count": 11104,
    "createAt": 1587600854342,
    "date": "2020-04-23"
  },
  {
    "count": 11105,
    "createAt": 1587687261272,
    "date": "2020-04-24"
  },
  {
    "count": 11109,
    "createAt": 1587773674643,
    "date": "2020-04-25"
  },
  {
    "count": 11109,
    "createAt": 1587860074423,
    "date": "2020-04-26"
  },
  {
    "count": 11110,
    "createAt": 1587946495990,
    "date": "2020-04-27"
  },
  {
    "count": 11113,
    "createAt": 1588032894609,
    "date": "2020-04-28"
  },
  {
    "count": 11116,
    "createAt": 1588119270640,
    "date": "2020-04-29"
  },
  {
    "count": 11119,
    "createAt": 1588205758317,
    "date": "2020-04-30"
  },
  {
    "count": 11122,
    "createAt": 1588292145937,
    "date": "2020-05-01"
  },
  {
    "count": 11122,
    "createAt": 1588378532925,
    "date": "2020-05-02"
  },
  {
    "count": 11122,
    "createAt": 1588464947461,
    "date": "2020-05-03"
  },
  {
    "count": 11122,
    "createAt": 1588551346299,
    "date": "2020-05-04"
  },
  {
    "count": 11122,
    "createAt": 1588659106784,
    "date": "2020-05-05"
  },
  {
    "count": 11122,
    "createAt": 1588724103098,
    "date": "2020-05-06"
  },
  {
    "count": 11123,
    "createAt": 1588810524690,
    "date": "2020-05-07"
  },
  {
    "count": 11124,
    "createAt": 1588896941221,
    "date": "2020-05-08"
  },
  {
    "count": 11130,
    "createAt": 1589026412622,
    "date": "2020-05-09"
  },
  {
    "count": 11130,
    "createAt": 1589069750911,
    "date": "2020-05-10"
  },
  {
    "count": 11130,
    "createAt": 1589156222880,
    "date": "2020-05-11"
  },
  {
    "count": 11134,
    "createAt": 1589263902846,
    "date": "2020-05-12"
  },
  {
    "count": 11134,
    "createAt": 1589329054647,
    "date": "2020-05-13"
  },
  {
    "count": 11135,
    "createAt": 1589415437670,
    "date": "2020-05-14"
  },
  {
    "count": 11137,
    "createAt": 1589501868337,
    "date": "2020-05-15"
  },
  {
    "count": 11140,
    "createAt": 1589588273933,
    "date": "2020-05-16"
  },
  {
    "count": 11140,
    "createAt": 1589674703754,
    "date": "2020-05-17"
  },
  {
    "count": 11140,
    "createAt": 1589761092702,
    "date": "2020-05-18"
  },
  {
    "count": 11150,
    "createAt": 1589847472342,
    "date": "2020-05-19"
  },
  {
    "count": 11161,
    "createAt": 1589933876734,
    "date": "2020-05-20"
  },
  {
    "count": 11166,
    "createAt": 1590020286702,
    "date": "2020-05-21"
  },
  {
    "count": 11171,
    "createAt": 1590106719752,
    "date": "2020-05-22"
  },
  {
    "count": 11174,
    "createAt": 1590193985181,
    "date": "2020-05-23"
  },
  {
    "count": 11174,
    "createAt": 1590280445803,
    "date": "2020-05-24"
  },
  {
    "count": 11174,
    "createAt": 1590366789870,
    "date": "2020-05-25"
  },
  {
    "count": 11179,
    "createAt": 1590453183243,
    "date": "2020-05-26"
  },
  {
    "count": 11185,
    "createAt": 1590539582003,
    "date": "2020-05-27"
  },
  {
    "count": 11188,
    "createAt": 1590626304585,
    "date": "2020-05-28"
  },
  {
    "count": 11193,
    "createAt": 1590712071106,
    "date": "2020-05-29"
  },
  {
    "count": 11194,
    "createAt": 1590798434908,
    "date": "2020-05-30"
  },
  {
    "count": 11194,
    "createAt": 1590884915689,
    "date": "2020-05-31"
  },
  {
    "count": 11194,
    "createAt": 1590971329473,
    "date": "2020-06-01"
  },
  {
    "count": 11197,
    "createAt": 1591057659494,
    "date": "2020-06-02"
  }
]